{
    "terminal.integrated.tabs.enabled": false,
    "[python]": {
        "editor.formatOnType": true
    },
    "workbench.colorTheme": "Default Dark+",
    "workbench.editorAssociations": {
        "*.pdf": "default"
    },
    "grammarly.files.include": [
        "**/*.tex"
    ],
    "grammarly.config.documentDialect": "american",
    "grammarly.config.documentDomain": "academic",
    "grammarly.config.suggestionCategories.informalPronounsAcademic": "on",
    "grammarly.config.suggestionCategories.conjugationAtStartOfSentence": "on",
    "grammarly.config.suggestionCategories.oxfordComma": "on",
    "grammarly.config.suggestionCategories.passiveVoice": "on",
    "grammarly.config.suggestionCategories.unnecessaryEllipses": "on",
    "terminal.integrated.shell.windows": "C:\\Windows\\System32\\WindowsPowerShell\\v1.0\\powershell.exe",
    "terminal.integrated.shellArgs.windows": ["-NoExit"]
}
